MANIFEST.in
setup.py
django_render/__init__.py
django_render/apps.py
django_render/decorators.py
django_render/response.py
django_render/telepath.py
django_render/views.py
django_render/templates/django_render/bootstrap.html
django_render/test/__init__.py
django_render/test/apps.py
django_render/test/settings.py
django_render/test/urls.py
django_render/test/tests/__init__.py
django_render/ui/__init__.py
django_render/ui/forms.py
pilrs.egg-info/PKG-INFO
pilrs.egg-info/SOURCES.txt
pilrs.egg-info/dependency_links.txt
pilrs.egg-info/not-zip-safe
pilrs.egg-info/requires.txt
pilrs.egg-info/top_level.txt